afmmech/__init__.py
afmmech/helpers.py
afmmech-4.2.dist-info/METADATA
afmmech-4.2.dist-info/WHEEL
afmmech-4.2.dist-info/top_level.txt
afmmech-4.2.dist-info/RECORD
